{
  "algolia_search": {
    "js": "algolia_search.ee1d31df.js"
  },
  "comments": {
    "js": "comments.a35f3711.js"
  },
  "details-polyfill": {
    "js": "details-polyfill.68e7f548.js"
  },
  "fuse_search": {
    "js": "fuse_search.bd3c8a5e.js"
  },
  "lunr_search": {
    "js": "lunr_search.cedbdc29.js"
  },
  "main": {
    "css": "main.5c2014c4.css",
    "js": "main.eb49ae54.js"
  },
  "rtl": {
    "css": "rtl.f49c88f3.css",
    "js": "rtl.63e83949.js"
  },
  "sidebar": {
    "js": "sidebar.1ea6985e.js"
  },
  "twemoji": {
    "js": "twemoji.92e9caab.js"
  }
}